{
	"id":	18,
	"visited":	0,
	"x":	0,
	"y":	3,
	"entities":	[{
			"type":	"startPoint",
			"name":	"",
			"x":	2880,
			"y":	0,
			"facing":	"FACING_RIGHT",
			"dx":	0,
			"dy":	0
		}, {
			"type":	"transferCube",
			"name":	"",
			"x":	2784,
			"y":	-48,
			"facing":	"FACING_RIGHT",
			"targetStage":	15,
			"targetFlag":	"bottom",
			"w":	5,
			"h":	1
		}, {
			"type":	"startPoint",
			"name":	"right",
			"x":	6080,
			"y":	2464,
			"facing":	"FACING_RIGHT",
			"dx":	0,
			"dy":	0
		}, {
			"type":	"player",
			"name":	"",
			"x":	2928,
			"y":	64,
			"facing":	"FACING_RIGHT",
			"health":	5,
			"maxHealth":	5,
			"ammo":	5,
			"maxAmmo":	5,
			"refillRate":	0.050000,
			"autoFire":	0,
			"hasDoubleJump":	0
		}, {
			"type":	"platform",
			"name":	"",
			"x":	2616,
			"y":	288,
			"facing":	"FACING_RIGHT",
			"sx":	2616,
			"sy":	288,
			"ex":	2616,
			"ey":	1016,
			"pause":	60,
			"speed":	2,
			"enabled":	1
		}, {
			"type":	"platform",
			"name":	"",
			"x":	2328,
			"y":	768,
			"facing":	"FACING_RIGHT",
			"sx":	2328,
			"sy":	768,
			"ex":	2328,
			"ey":	1016,
			"pause":	60,
			"speed":	2,
			"enabled":	1
		}, {
			"type":	"door",
			"name":	"tfDoor1",
			"x":	3184,
			"y":	960,
			"facing":	"FACING_RIGHT",
			"open":	0,
			"requires":	"DR_REMOTE",
			"sx":	3184,
			"sy":	960,
			"ex":	3184,
			"ey":	868
		}, {
			"type":	"door",
			"name":	"tfDoor2",
			"x":	3904,
			"y":	1344,
			"facing":	"FACING_RIGHT",
			"open":	0,
			"requires":	"DR_REMOTE",
			"sx":	3904,
			"sy":	1344,
			"ex":	3904,
			"ey":	1252
		}, {
			"type":	"door",
			"name":	"tfDoor3",
			"x":	4576,
			"y":	1680,
			"facing":	"FACING_RIGHT",
			"open":	0,
			"requires":	"DR_REMOTE",
			"sx":	4576,
			"sy":	1680,
			"ex":	4576,
			"ey":	1588
		}, {
			"type":	"door",
			"name":	"tfDoor4",
			"x":	5344,
			"y":	2160,
			"facing":	"FACING_RIGHT",
			"open":	0,
			"requires":	"DR_REMOTE",
			"sx":	5344,
			"sy":	2160,
			"ex":	5344,
			"ey":	2068
		}, {
			"type":	"platform",
			"name":	"",
			"x":	1992,
			"y":	432,
			"facing":	"FACING_RIGHT",
			"sx":	1992,
			"sy":	432,
			"ex":	1992,
			"ey":	728,
			"pause":	60,
			"speed":	2,
			"enabled":	1
		}, {
			"type":	"door",
			"name":	"tfDoor1",
			"x":	1792,
			"y":	864,
			"facing":	"FACING_RIGHT",
			"open":	0,
			"requires":	"DR_REMOTE",
			"sx":	1792,
			"sy":	864,
			"ex":	1792,
			"ey":	772
		}, {
			"type":	"door",
			"name":	"",
			"x":	1072,
			"y":	720,
			"facing":	"FACING_RIGHT",
			"open":	0,
			"requires":	"DR_KEY",
			"sx":	1072,
			"sy":	720,
			"ex":	1072,
			"ey":	628
		}, {
			"type":	"door",
			"name":	"",
			"x":	976,
			"y":	336,
			"facing":	"FACING_RIGHT",
			"open":	0,
			"requires":	"DR_KEY",
			"sx":	976,
			"sy":	336,
			"ex":	976,
			"ey":	244
		}, {
			"type":	"door",
			"name":	"bottleDoor",
			"x":	976,
			"y":	96,
			"facing":	"FACING_RIGHT",
			"open":	0,
			"requires":	"DR_REMOTE",
			"sx":	976,
			"sy":	96,
			"ex":	976,
			"ey":	4
		}, {
			"type":	"platform",
			"name":	"",
			"x":	504,
			"y":	432,
			"facing":	"FACING_RIGHT",
			"sx":	504,
			"sy":	432,
			"ex":	504,
			"ey":	872,
			"pause":	60,
			"speed":	2,
			"enabled":	1
		}, {
			"type":	"trafficLight",
			"name":	"",
			"x":	1696,
			"y":	760,
			"facing":	"FACING_RIGHT",
			"targetName":	"tfDoor1",
			"on":	0
		}, {
			"type":	"trafficLight",
			"name":	"",
			"x":	4496,
			"y":	904,
			"facing":	"FACING_RIGHT",
			"targetName":	"tfDoor3",
			"on":	0
		}, {
			"type":	"trafficLight",
			"name":	"",
			"x":	5272,
			"y":	904,
			"facing":	"FACING_RIGHT",
			"targetName":	"tfDoor4",
			"on":	0
		}, {
			"type":	"trafficLight",
			"name":	"",
			"x":	6040,
			"y":	1384,
			"facing":	"FACING_RIGHT",
			"targetName":	"tfDoor5",
			"on":	0
		}, {
			"type":	"door",
			"name":	"",
			"x":	5536,
			"y":	912,
			"facing":	"FACING_RIGHT",
			"open":	0,
			"requires":	"DR_KEY",
			"sx":	5536,
			"sy":	912,
			"ex":	5536,
			"ey":	820
		}, {
			"type":	"chest",
			"name":	"",
			"x":	5432,
			"y":	976,
			"facing":	"FACING_RIGHT",
			"open":	0,
			"coins":	4,
			"nextRefill":	0,
			"found":	0
		}, {
			"type":	"chest",
			"name":	"",
			"x":	4680,
			"y":	1120,
			"facing":	"FACING_RIGHT",
			"open":	0,
			"coins":	6,
			"nextRefill":	0,
			"found":	0
		}, {
			"type":	"chest",
			"name":	"",
			"x":	3976,
			"y":	928,
			"facing":	"FACING_RIGHT",
			"open":	0,
			"coins":	7,
			"nextRefill":	0,
			"found":	0
		}, {
			"type":	"chest",
			"name":	"",
			"x":	6016,
			"y":	1936,
			"facing":	"FACING_RIGHT",
			"open":	0,
			"coins":	3,
			"nextRefill":	0,
			"found":	0
		}, {
			"type":	"waterBottle",
			"name":	"",
			"x":	472,
			"y":	151,
			"facing":	"FACING_RIGHT"
		}, {
			"type":	"piggyBank",
			"name":	"",
			"x":	1072,
			"y":	160,
			"facing":	"FACING_RIGHT",
			"requiredCoins":	100,
			"targetName":	"bottleDoor"
		}, {
			"type":	"platform",
			"name":	"",
			"x":	5424,
			"y":	1440,
			"facing":	"FACING_RIGHT",
			"sx":	5424,
			"sy":	1440,
			"ex":	5424,
			"ey":	1648,
			"pause":	60,
			"speed":	2,
			"enabled":	1
		}, {
			"type":	"key",
			"name":	"",
			"x":	1864,
			"y":	992,
			"facing":	"FACING_RIGHT"
		}, {
			"type":	"key",
			"name":	"",
			"x":	472,
			"y":	1000,
			"facing":	"FACING_RIGHT"
		}, {
			"type":	"platform",
			"name":	"",
			"x":	5208,
			"y":	1536,
			"facing":	"FACING_RIGHT",
			"sx":	5208,
			"sy":	1536,
			"ex":	5208,
			"ey":	2200,
			"pause":	60,
			"speed":	2,
			"enabled":	1
		}, {
			"type":	"trafficLight",
			"name":	"",
			"x":	3824,
			"y":	1096,
			"facing":	"FACING_RIGHT",
			"targetName":	"tfDoor2",
			"on":	0
		}, {
			"type":	"door",
			"name":	"tfDoor5",
			"x":	6040,
			"y":	2400,
			"facing":	"FACING_RIGHT",
			"open":	0,
			"requires":	"DR_REMOTE",
			"sx":	6040,
			"sy":	2400,
			"ex":	6040,
			"ey":	2308
		}, {
			"type":	"redFlyingCyclops",
			"name":	"",
			"x":	5696,
			"y":	1568,
			"facing":	"FACING_RIGHT",
			"isMonster":	1
		}, {
			"type":	"redFlyingCyclops",
			"name":	"",
			"x":	5088,
			"y":	864,
			"facing":	"FACING_RIGHT",
			"isMonster":	1
		}, {
			"type":	"redFlyingCyclops",
			"name":	"",
			"x":	4080,
			"y":	856,
			"facing":	"FACING_RIGHT",
			"isMonster":	1
		}, {
			"type":	"redFlyingCyclops",
			"name":	"",
			"x":	3680,
			"y":	1040,
			"facing":	"FACING_RIGHT",
			"isMonster":	1
		}, {
			"type":	"redFlyingCyclops",
			"name":	"",
			"x":	1952,
			"y":	872,
			"facing":	"FACING_RIGHT",
			"isMonster":	1
		}, {
			"type":	"redFlyingCyclops",
			"name":	"",
			"x":	1136,
			"y":	304,
			"facing":	"FACING_RIGHT",
			"isMonster":	1
		}, {
			"type":	"redFlyingCyclops",
			"name":	"",
			"x":	1496,
			"y":	640,
			"facing":	"FACING_RIGHT",
			"isMonster":	1
		}, {
			"type":	"redFlyingCyclops",
			"name":	"",
			"x":	5888,
			"y":	936,
			"facing":	"FACING_RIGHT",
			"isMonster":	1
		}, {
			"type":	"transferCube",
			"name":	"",
			"x":	6144,
			"y":	2400,
			"facing":	"FACING_RIGHT",
			"targetStage":	19,
			"targetFlag":	"left",
			"w":	1,
			"h":	2
		}, {
			"type":	"key",
			"name":	"",
			"x":	2360,
			"y":	2120,
			"facing":	"FACING_RIGHT"
		}],
	"map":	{
		"data":	"eJztmlluwyAUAK/SIziRuP/VqnyksfHb8MKDZjSK1NiAmQdma5afZcOjA32fFq3Lu0b1Fft6nH0JJd0+7n+euuQR7PP8x7CX/EsTHx8vxWNA+6ve/yKWpZUwjv01/kUpa9s3HlXqMWhrZ8tey1nfzza+1r8YZcn3s409//JX8wjrstbjnXR/Dn+9re2+ER3/so3xxx9/3b8ewb7Nv76yjcH3+UdjIO8cPvln9n87SDP8Z6aP9JL2nnN8RFr3uWj+6NPO+I7tr+9u6x3cPP7x+1KOegcj2UdHySPRibTIUt2JvZOx8V8fLbZp7vJfU6p7Vm0fSuxsf3+Ho+2C2k6O9JMiy38bAf9Msb3985AjYKXzzxRn8pf33vb45/Wd/fthl53rL/UB/VypmPmsvKO2v2TinyvpEdiuWObw98d47Qw13nfG9td6s20v5ZvV34qAfX4u9534+JjtvTaRV30tkXt/09YmI/trTn5t/0P/j0VAS1tUv1n9/fkt5jev/zXz28z+3rwo+bXv/8amLQJe3vn89zNZ3D+yPsq2OxKPuL+/ts62uTYCXur/4W+tj7zxoZ+/XZMI7RGwzg56rn/Pux+LQPQ3Kff5X2Vu1c9KbdvP5y+jzYb++fhs/tb5+4vWk5O7/fetUk79HXli3L7X+PeKwfOZ/4n+9lJeYcq5+0TwxXNZ0j9H23/fGzMimIcVgW/wb9m5Ztc0OwLZ9bwzApH/e2fXsjf4AwAAAAAAAAAAAAAAAAAAAAAAAAAAAAAAAAAAAAAAAAAAAAAA9OUXk5syUw=",
		"eLen":	796,
		"cLen":	595,
		"dLen":	32900
	}
}
