{
	"entities":	[{
			"type":	"player",
			"x":	88,
			"y":	592,
			"facing":	"right"
		}, {
			"type":	"greenHorse",
			"x":	584,
			"y":	448
		}, {
			"type":	"transferCube",
			"x":	1296,
			"y":	528,
			"targetStage":	1,
			"targetFlag":	"topLeft"
		}, {
			"type":	"transferCube",
			"x":	1296,
			"y":	576,
			"targetStage":	1,
			"targetFlag":	"topLeft"
		}, {
			"type":	"startPoint",
			"x":	1248,
			"y":	592,
			"name":	"rightFlag"
		}],
	"map":	{
		"data":	"eJzt2LENgDAMRcFVGIEU3n81CioqhwgJ8Tldm4KnOIUZ21iwx1hp0f/2V+vXr1+/fv36n+mvRnZ/tSf7E1+UdJer/d3kX19ARU3C3fuvX+9/Fbj/zk3z+QIS9/8x9fZT/38AAAAAAAAAAAAAAAAAAAAAAAAAAAAAAAAAAAAw5wAYMgK",
		"eLen":	176,
		"cLen":	132,
		"dLen":	32768
	}
}
